lunisolar/__init__.py
lunisolar/constants.py
lunisolar/lunisolar.py
pycalcal/__init__.py
pycalcal/pycalcal.py
pycalcal/wrappers.py
lunisolar_upgraded-0.1.4.dist-info/LICENSE
lunisolar_upgraded-0.1.4.dist-info/METADATA
lunisolar_upgraded-0.1.4.dist-info/WHEEL
lunisolar_upgraded-0.1.4.dist-info/top_level.txt
lunisolar_upgraded-0.1.4.dist-info/RECORD
