Metadata-Version: 2.1
Name: lunisolar-upgraded
Version: 0.1.4
Summary: A library to handle the Chinese calendar
Home-page: https://github.com/yen223/lunisolar
Author: Lee Wei Yen
Author-email: lee@weiyen.me
Classifier: Programming Language :: Python
Classifier: License :: OSI Approved :: MIT License
Classifier: Operating System :: OS Independent
Classifier: Development Status :: 4 - Beta
Classifier: Intended Audience :: Developers
Classifier: Programming Language :: Python :: 2.7
Classifier: Topic :: Software Development :: Libraries
Classifier: Topic :: Utilities
Classifier: Topic :: Sociology
Classifier: Topic :: Software Development :: Internationalization
License-File: LICENSE
Requires-Dist: mpmath
